Workbook
Name aporte: Ferramenta!$D$19
Name dividendos: Ferramenta!$D$23
Name patrimonio: Ferramenta!$D$22
Name qtd_anos: Ferramenta!$D$20
Name rendimento_carteira: Ferramenta!$D$14
Name salario: Ferramenta!$D$13
Name sugestao_invest: Ferramenta!$D$15
Name taxa_mensal: Ferramenta!$D$21

Sheet Ferramenta
B12: CONFIGURAÇÕES
B13: Salário | D13: 5000
B14: Rendimento Carteira | D14: 0.009
B15: Sugestão de Investimento (30%) | D15: =D13*30% -> 1500
B18: INVESTIMENTO MENSAL
B19: Quanto investir por mês? | D19: 500
B20: Por quantos anos? | D20: 10
B21: Qual a taxa de rendimento mensal? | D21: 0.01079
B22: Patrimônio acumulado: | D22: =FV(taxa_mensal,qtd_anos*12,aporte*-1) -> 121642.11
B23: Dividendos Mensais: | D23: =patrimonio*rendimento_carteira -> 1094.779
B26: CENÁRIOS | D26: DIVIDENDOS
A27: 2 | B27: Quanto em 2 anos? | C27: =FV($D$21,$A27*12,$D$19*-1) -> 13613.814 | D27: =C27*rendimento_carteira -> 122.52432
A28: 5 | B28: Quanto em 5 anos? | C28: =FV($D$21,$A28*12,$D$19*-1) -> 41888.457 | D28: =C28*rendimento_carteira -> 376.99611
A29: 10 | B29: Quanto em 10 anos? | C29: =FV($D$21,$A29*12,$D$19*-1) -> 121642.11 | D29: =C29*rendimento_carteira -> 1094.779
A30: 20 | B30: Quanto em 20 anos? | C30: =FV($D$21,$A30*12,$D$19*-1) -> 562599.2 | D30: =C30*rendimento_carteira -> 5063.3928
A31: 30 | B31: Quanto em 30 anos? | C31: =FV($D$21,$A31*12,$D$19*-1) -> 2161084.8 | D31: =C31*rendimento_carteira -> 19449.763
A32: 50 | B32: Quanto em 50 anos? | C32: =FV($D$21,$A32*12,$D$19*-1) -> 28961179 | D32: =C32*rendimento_carteira -> 260650.61
B35: PERFIL | C35: Moderado
B36: VALOR INVESTIDO POR MÊS | C36: =aporte -> 500
B39: TIPO DE FII | C39: PERCENTUAL SUGERIDO | D39: VALORES
B40: PAPEL | C40: =VLOOKUP($C$35&"-"&B40,Plan1!$A:$D,4,FALSE) -> 0.32 | D40: =C40*C$36 -> 160
B41: TIJOLO | C41: =VLOOKUP($C$35&"-"&B41,Plan1!$A:$D,4,FALSE) -> 0.35 | D41: =C41*C$36 -> 175
B42: HÍBRIDOS | C42: =VLOOKUP($C$35&"-"&B42,Plan1!$A:$D,4,FALSE) -> 0.08 | D42: =C42*C$36 -> 40
B43: FOFs | C43: =VLOOKUP($C$35&"-"&B43,Plan1!$A:$D,4,FALSE) -> 0.1 | D43: =C43*C$36 -> 50
B44: DESENVOLVIMENTO | C44: =VLOOKUP($C$35&"-"&B44,Plan1!$A:$D,4,FALSE) -> 0.1 | D44: =C44*C$36 -> 50
B45: HOTELARIAS | C45: =VLOOKUP($C$35&"-"&B45,Plan1!$A:$D,4,FALSE) -> 0.05 | D45: =C45*C$36 -> 25
D46: =SUM(D40:D45) -> 500

Sheet Plan1
A1: CHAVE | B1: PERFIL | C1: TIPO DE FII | D1: %
A2: =B2&"-"&C2 -> Conservador-PAPEL | B2: Conservador | C2: PAPEL | D2: 0.35
A3: =B3&"-"&C3 -> Conservador-TIJOLO | B3: Conservador | C3: TIJOLO | D3: 0.45
A4: =B4&"-"&C4 -> Conservador-HÍBRIDOS | B4: Conservador | C4: HÍBRIDOS | D4: 0.1
A5: =B5&"-"&C5 -> Conservador-FOFs | B5: Conservador | C5: FOFs | D5: 0.1
A6: =B6&"-"&C6 -> Conservador-DESENVOLVIMENTO | B6: Conservador | C6: DESENVOLVIMENTO | D6: 0
A7: =B7&"-"&C7 -> Conservador-HOTELARIAS | B7: Conservador | C7: HOTELARIAS | D7: 0
A8: =B8&"-"&C8 -> Moderado-PAPEL | B8: Moderado | C8: PAPEL | D8: 0.32
A9: =B9&"-"&C9 -> Moderado-TIJOLO | B9: Moderado | C9: TIJOLO | D9: 0.35
A10: =B10&"-"&C10 -> Moderado-HÍBRIDOS | B10: Moderado | C10: HÍBRIDOS | D10: 0.08
A11: =B11&"-"&C11 -> Moderado-FOFs | B11: Moderado | C11: FOFs | D11: 0.1
A12: =B12&"-"&C12 -> Moderado-DESENVOLVIMENTO | B12: Moderado | C12: DESENVOLVIMENTO | D12: 0.1
A13: =B13&"-"&C13 -> Moderado-HOTELARIAS | B13: Moderado | C13: HOTELARIAS | D13: 0.05
... A19: =B19&"-"&C19 -> Agressivo-HOTELARIAS | B19: Agressivo | C19: HOTELARIAS | D19: 0.1
